recur7down/__init__.py
recur7down/base.py
recur7down/diary.py
recur7down/html.py
recur7down/parse_diary.py
recur7down/products.py
recur7down/transaction.py
recur7down-0.2.2.3.dist-info/DESCRIPTION.rst
recur7down-0.2.2.3.dist-info/METADATA
recur7down-0.2.2.3.dist-info/RECORD
recur7down-0.2.2.3.dist-info/WHEEL
recur7down-0.2.2.3.dist-info/entry_points.txt
recur7down-0.2.2.3.dist-info/metadata.json
recur7down-0.2.2.3.dist-info/top_level.txt
