Metadata-Version: 2.0
Name: recur7down
Version: 0.2.2.3
Summary: recursive web scraper code for work related project
Home-page: https://github.com/shichaoji/recur7down
Author: Shichao(Richard) Ji
Author-email: jshichao@vt.edu
License: MIT
Download-URL: https://github.com/shichaoji/recur7down/archive/0.1.tar.gz
Keywords: datarequests,python,scrapy
Platform: UNKNOWN
Classifier: License :: OSI Approved :: MIT License
Classifier: Programming Language :: Python :: 2
Requires-Dist: Pandas
Requires-Dist: json2df
